flask_structured_api/__init__.py
flask_structured_api/__version__.py
flask_structured_api/_version.py
flask_structured_api/factory.py
flask_structured_api/main.py
flask_structured_api/api/.gitkeep
flask_structured_api/api/core/__init__.py
flask_structured_api/api/core/root.py
flask_structured_api/api/core/v1/__init__.py
flask_structured_api/api/core/v1/routes.py
flask_structured_api/api/core/v1/endpoints/__init__.py
flask_structured_api/api/core/v1/endpoints/auth.py
flask_structured_api/api/core/v1/endpoints/health.py
flask_structured_api/api/core/v1/endpoints/storage.py
flask_structured_api/api/custom/__init__.py
flask_structured_api/api/custom/v1/__init__.py
flask_structured_api/api/custom/v1/endpoints/__init__.py
flask_structured_api/api/custom/v1/endpoints/hello.py
flask_structured_api/core/__init__.py
flask_structured_api/core/middleware.py
flask_structured_api/core/ai/__init__.py
flask_structured_api/core/ai/base.py
flask_structured_api/core/ai/models.py
flask_structured_api/core/ai/parser.py
flask_structured_api/core/ai/service.py
flask_structured_api/core/ai/prompts/__init__.py
flask_structured_api/core/ai/prompts/base.py
flask_structured_api/core/ai/validation/__init__.py
flask_structured_api/core/ai/validation/base.py
flask_structured_api/core/auth/__init__.py
flask_structured_api/core/cache/__init__.py
flask_structured_api/core/cli/__init__.py
flask_structured_api/core/cli/api_keys.py
flask_structured_api/core/cli/backup.py
flask_structured_api/core/cli/tokens.py
flask_structured_api/core/config/__init__.py
flask_structured_api/core/config/settings.py
flask_structured_api/core/db/__init__.py
flask_structured_api/core/db/engine.py
flask_structured_api/core/db/migrations.py
flask_structured_api/core/enums/__init__.py
flask_structured_api/core/exceptions/__init__.py
flask_structured_api/core/exceptions/ai.py
flask_structured_api/core/exceptions/auth.py
flask_structured_api/core/exceptions/base.py
flask_structured_api/core/exceptions/validation.py
flask_structured_api-0.1.3.dist-info/LICENSE
flask_structured_api-0.1.3.dist-info/METADATA
flask_structured_api-0.1.3.dist-info/NOTICE.md
flask_structured_api-0.1.3.dist-info/WHEEL
flask_structured_api-0.1.3.dist-info/top_level.txt
flask_structured_api-0.1.3.dist-info/RECORD
