Metadata-Version: 2.1
Name: flask-structured-api
Version: 0.1.3
Summary: A structured Flask API boilerplate with built-in AI capabilities, featuring SQLModel ORM and Pydantic validation
Home-page: https://github.com/julianfleck/flask-structured-api
Author: Julian Fleck
Author-email: Julian Fleck <dev@julianfleck.net>
License: Apache-2.0
Project-URL: Homepage, https://github.com/julianfleck/flask-structured-api
Project-URL: Documentation, https://github.com/julianfleck/flask-structured-api#readme
Project-URL: Repository, https://github.com/julianfleck/flask-structured-api.git
Project-URL: Issues, https://github.com/julianfleck/flask-structured-api/issues
Keywords: flask,api,boilerplate,ai,structured,sqlmodel,pydantic,orm,validation,postgresql,redis,celery,openapi,jwt,authentication,auth
Classifier: Development Status :: 4 - Beta
Classifier: Framework :: Flask
Classifier: Intended Audience :: Developers
Classifier: License :: OSI Approved :: Apache Software License
Classifier: Operating System :: OS Independent
Classifier: Programming Language :: Python :: 3.10
Classifier: Programming Language :: Python :: 3.11
Classifier: Topic :: Software Development :: Libraries :: Application Frameworks
Classifier: Topic :: Database :: Front-Ends
Classifier: Topic :: Internet :: WWW/HTTP :: HTTP Servers
Requires-Python: >=3.10
License-File: LICENSE
License-File: NOTICE.md
Requires-Dist: Flask<4.0.0,>=3.1.0
Requires-Dist: flask-openapi3<5.0.0,>=4.0.2
Requires-Dist: flask-sqlalchemy<4.0.0,>=3.1.1
Requires-Dist: flask-migrate<5.0.0,>=4.0.7
Requires-Dist: Werkzeug<4.0.0,>=3.1.3
Requires-Dist: gunicorn<22.0.0,>=21.2.0
Requires-Dist: SQLAlchemy<3.0.0,>=2.0.36
Requires-Dist: sqlmodel<0.1.0,>=0.0.22
Requires-Dist: psycopg2-binary<3.0.0,>=2.9.9
Requires-Dist: alembic<2.0.0,>=1.13.1
Requires-Dist: PyJWT<3.0.0,>=2.10.0
Requires-Dist: passlib<2.0.0,>=1.7.4
Requires-Dist: flask-cors<5.0.0,>=4.0.0
Requires-Dist: redis<6.0.0,>=5.2.0
Requires-Dist: celery<6.0.0,>=5.3.6
Requires-Dist: flower<3.0.0,>=2.0.1
Requires-Dist: python-dotenv<2.0.0,>=1.0.0
Requires-Dist: email-validator<3.0.0,>=2.1.0
Requires-Dist: pydantic[email]<3.0.0,>=2.5.0
Requires-Dist: pydantic-settings<3.0.0,>=2.6.1
Requires-Dist: psutil<7.0.0,>=6.1.0
Requires-Dist: prometheus-client<1.0.0,>=0.19.0
Provides-Extra: dev
Requires-Dist: debugpy<2.0.0,>=1.8.8; extra == "dev"
Requires-Dist: black<25.0.0,>=24.1.1; extra == "dev"
Requires-Dist: isort<6.0.0,>=5.13.2; extra == "dev"
Requires-Dist: flake8<8.0.0,>=7.0.0; extra == "dev"
Requires-Dist: mypy<2.0.0,>=1.8.0; extra == "dev"
Requires-Dist: pre-commit<4.0.0,>=3.6.0; extra == "dev"
